{"cameraMode":{"drawMode":0,"name":"Shaded","section":"Shading Mode"},"sceneLighting":true,"audioPlay":false,"sceneViewState":{"showFog":true,"showMaterialUpdate":false,"showSkybox":true,"showFlares":true,"showImageEffects":true,"showParticleSystems":true},"in2DMode":false,"pivot":{"x":21.805143356323243,"y":6.218596935272217,"z":4.84016752243042},"rotation":{"x":-0.21955052018165589,"y":0.49263039231300356,"z":-0.12999454140663148,"w":-0.8320019245147705},"size":0.8660283088684082,"orthographic":false}